{
  "version": 1,
  "author": "Anonymous maker",
  "editor": "wokwi",
  "parts": [
    {
      "type": "board-esp32-devkit-c-v4",
      "id": "esp",
      "top": -48,
      "left": -81.56,
      "attrs": { "builder": "esp-idf" }
    },
    { "type": "wokwi-pir-motion-sensor", "id": "pir1", "top": 32.8, "left": 50.22, "attrs": {} },
    { "type": "wokwi-gas-sensor", "id": "gas1", "top": 2.7, "left": -338.6, "attrs": {} },
    { "type": "wokwi-dht22", "id": "dht1", "top": 211.5, "left": -82.2, "attrs": {} },
    {
      "type": "wokwi-led",
      "id": "led1",
      "top": -157.2,
      "left": -399.4,
      "attrs": { "color": "green" }
    },
    {
      "type": "wokwi-led",
      "id": "led2",
      "top": -157.2,
      "left": -303.4,
      "attrs": { "color": "red" }
    },
    {
      "type": "wokwi-led",
      "id": "led3",
      "top": -157.2,
      "left": -351.4,
      "attrs": { "color": "yellow" }
    },
    {
      "type": "wokwi-pushbutton",
      "id": "btn1",
      "top": -3.4,
      "left": 249.6,
      "attrs": { "color": "green", "xray": "1" }
    }
  ],
  "connections": [
    [ "esp:TX", "$serialMonitor:RX", "", [] ],
    [ "esp:RX", "$serialMonitor:TX", "", [] ],
    [ "gas1:VCC", "esp:5V", "red", [ "h9.6", "v133.5" ] ],
    [ "gas1:GND", "esp:GND.1", "black", [ "h19.2", "v56.8" ] ],
    [ "gas1:DOUT", "esp:12", "green", [ "h28.8", "v66.9" ] ],
    [ "dht1:VCC", "esp:5V", "red", [ "v9.6", "h-48", "v-182.4" ] ],
    [ "dht1:GND", "esp:GND.1", "black", [ "v48", "h-134.4", "v-268.8" ] ],
    [ "dht1:SDA", "esp:27", "green", [ "v28.8", "h-95.9", "v-278.4" ] ],
    [ "pir1:VCC", "esp:5V", "red", [ "v48", "h-192", "v0", "h-9.6", "v-19.2" ] ],
    [ "pir1:GND", "esp:GND.1", "black", [ "v57.6", "h-278.66", "v-76.8" ] ],
    [ "pir1:OUT", "esp:2", "green", [ "v19.2", "h-67.34", "v-28.8" ] ],
    [ "gas1:AOUT", "esp:34", "green", [ "h0" ] ]
  ],
  "dependencies": {}
}